[
  {
    "fio": "Григорьева Светлана",
    "rating": 65,
    "age": 21,
    "photoUrl": "avatar1.jpg",
    "speciality": "Прикладная информатика",
    "group": "ПИ-101"
  },
  {
    "fio": "Степанова Анна",
    "rating": 29,
    "age": 20,
    "speciality": "Прикладная информатика",
    "group": "ПИ-101"
  },
  {
    "fio": "Сундар Пичаи",
    "rating": 80,
    "age": 19,
    "speciality": "Прикладная информатика",
    "group": "ПИ-101"
  },
  {
    "fio": "Алексеев Александр",
    "rating": 46,
    "age": 22,
    "speciality": "Прикладная информатика",
    "group": "ПИ-101"
  }
]